plantower/__init__.py
plantower/plantower.py
plantower-0.0.11.dist-info/LICENSE
plantower-0.0.11.dist-info/METADATA
plantower-0.0.11.dist-info/WHEEL
plantower-0.0.11.dist-info/top_level.txt
plantower-0.0.11.dist-info/RECORD
