Metadata-Version: 2.1
Name: plantower
Version: 0.0.11
Summary: An interface for plantower particulate matter sensors
Home-page: https://github.com/FEEprojects/plantower
Author: Philip Basford
Author-email: P.J.Basford@soton.ac.uk
License: UNKNOWN
Platform: UNKNOWN
Classifier: Programming Language :: Python :: 3
Classifier: License :: OSI Approved :: MIT License
Classifier: Operating System :: OS Independent
Requires-Python: >=3.3, <4
Requires-Dist: pyserial
